retryable_requests/__init__.py
retryable_requests/py.typed
retryable_requests/session.py
retryable_requests-0.1.2.dist-info/LICENSE
retryable_requests-0.1.2.dist-info/METADATA
retryable_requests-0.1.2.dist-info/WHEEL
retryable_requests-0.1.2.dist-info/top_level.txt
retryable_requests-0.1.2.dist-info/RECORD
